aprep/__init__.py
aprep/_modidx.py
aprep/core.py
aprep-0.0.3.dist-info/LICENSE
aprep-0.0.3.dist-info/METADATA
aprep-0.0.3.dist-info/WHEEL
aprep-0.0.3.dist-info/entry_points.txt
aprep-0.0.3.dist-info/top_level.txt
aprep-0.0.3.dist-info/RECORD
