Metadata-Version: 2.1
Name: aprep
Version: 0.0.3
Summary: aprep
Home-page: https://github.com/dsm-72/aprep
Author: dsm-72
Author-email: sumner.magruder@yale.edu
License: Apache Software License 2.0
Keywords: nbdev jupyter notebook python attr prep attributes preparation data science args aprep ispec ropts ranked arguments kws
Classifier: Development Status :: 4 - Beta
Classifier: Intended Audience :: Developers
Classifier: Natural Language :: English
Classifier: Programming Language :: Python :: 3.11
Classifier: License :: OSI Approved :: Apache Software License
Requires-Python: >=3.11
License-File: LICENSE
Requires-Dist: atyp
Requires-Dist: ropts
Requires-Dist: ispec
Provides-Extra: dev
